Metadata-Version: 2.1
Name: cellfinder-napari
Version: 1.0.2
Summary: Efficient cell detection in large images
Author-email: Adam Tyson <code@adamltyson.com>
License: BSD-3-Clause
Project-URL: Homepage, https://brainglobe.info/cellfinder
Project-URL: Source Code, https://github.com/brainglobe/cellfinder-napari
Project-URL: Bug Tracker, https://github.com/brainglobe/cellfinder-napari/issues
Project-URL: Documentation, https://docs.brainglobe.info/cellfinder-napari/
Project-URL: User Support, https://forum.image.sc/tag/brainglobe
Classifier: Development Status :: 4 - Beta
Classifier: Intended Audience :: Developers
Classifier: Intended Audience :: Science/Research
Classifier: Operating System :: OS Independent
Classifier: Programming Language :: Python
Classifier: Programming Language :: Python :: 3
Classifier: Programming Language :: Python :: 3.8
Classifier: Programming Language :: Python :: 3.9
Classifier: Programming Language :: Python :: 3.10
Classifier: Topic :: Scientific/Engineering :: Image Recognition
Requires-Python: >=3.8
License-File: LICENSE
Requires-Dist: brainglobe-napari-io
Requires-Dist: cellfinder-core >=0.3
Requires-Dist: brainglobe-utils
Requires-Dist: magicgui
Requires-Dist: napari
Requires-Dist: napari-ndtiffs
Requires-Dist: napari-plugin-engine >=0.1.4
Requires-Dist: numpy
Requires-Dist: pooch >=1
Requires-Dist: qtpy
Requires-Dist: scikit-image
Requires-Dist: tifffile
Provides-Extra: dev
Requires-Dist: black ; extra == 'dev'
Requires-Dist: gitpython ; extra == 'dev'
Requires-Dist: pre-commit ; extra == 'dev'
Requires-Dist: pytest ; extra == 'dev'
Requires-Dist: pytest-cov ; extra == 'dev'
Requires-Dist: pytest-qt ; extra == 'dev'
